tblink_rpc_hdl-0.0.0.dist-info/top_level.txt
tblink_rpc_hdl-0.0.0.dist-info/entry_points.txt
tblink_rpc_hdl-0.0.0.dist-info/LICENSE
tblink_rpc_hdl-0.0.0.dist-info/METADATA
tblink_rpc_hdl-0.0.0.dist-info/RECORD
tblink_rpc_hdl-0.0.0.dist-info/WHEEL
tblink_rpc_hdl/__main__.py
tblink_rpc_hdl/__init__.py
tblink_rpc_hdl/tblink_rpc_hdl_stub.cpython-37m-x86_64-linux-gnu.so
